{
  "index": "Introduction",
  "guide": "Guide",
  "-- Themes --": {
    "type": "separator",
    "title": "Themes"
  },
  "docs-theme": "Docs Theme",
  "blog-theme": "Blog Theme",
  "custom-theme": "Custom Theme",
  "-- About --": {
    "type": "separator",
    "title": "More"
  },
  "about link": {
    "title": "About Nextra",
    "href": "/about"
  },
  "Next.js link": {
    "title": "Next.js Docs ↗",
    "href": "https://nextjs.org?utm_source=nextra.site&utm_medium=referral&utm_campaign=sidebar",
    "newWindow": true
  }
}
